{
    "intrinsics": [
        [
            1365.750227768863,
            0.0,
            1296.0
        ],
        [
            0.0,
            1365.750227768863,
            972.0
        ],
        [
            0.0,
            0.0,
            1.0
        ]
    ],
    "distortion": [
        -0.3614559666186334,
        0.19810521887279448,
        0.0,
        0.0,
        -0.04844977179521971
    ],
    "rotation": [
        [
            -0.04096285301739866,
            -0.999043499393788,
            0.01530133953904067
        ],
        [
            0.18330920074700546,
            -0.022568553242678202,
            -0.9827962135285351
        ],
        [
            0.9822014974505835,
            -0.03745326051956499,
            0.18405833771466168
        ]
    ],
    "translation": [
        -2.2557907942555278,
        2.030426374561324,
        -7.929347427348549
    ],
    "origin_gps": {
        "lat": 43.07063697146,
        "lon": -89.40685704184578,
        "alt": 325.1792
    }
}